pysealer/__init__.py
pysealer/_pysealer.cpython-38-i386-linux-gnu.so
pysealer/add_decorators.py
pysealer/check_decorators.py
pysealer/cli.py
pysealer/dummy_decorators.py
pysealer/git_diff.py
pysealer/github_secrets.py
pysealer/remove_decorators.py
pysealer/setup.py
pysealer-0.6.0.dist-info/METADATA
pysealer-0.6.0.dist-info/WHEEL
pysealer-0.6.0.dist-info/entry_points.txt
pysealer-0.6.0.dist-info/licenses/LICENSE
pysealer.libs/libgcc_s-8c2f5de4.so.1
pysealer-0.6.0.dist-info/RECORD
