Metadata-Version: 2.4
Name: pysealer
Version: 0.6.0
Classifier: Development Status :: 3 - Alpha
Classifier: Intended Audience :: Developers
Classifier: License :: OSI Approved :: MIT License
Classifier: Programming Language :: Python :: 3
Classifier: Programming Language :: Python :: 3.8
Classifier: Programming Language :: Python :: 3.9
Classifier: Programming Language :: Python :: 3.10
Classifier: Programming Language :: Python :: 3.11
Classifier: Programming Language :: Python :: 3.12
Classifier: Programming Language :: Rust
Classifier: Programming Language :: Python :: Implementation :: CPython
Classifier: Programming Language :: Python :: Implementation :: PyPy
Classifier: Topic :: Security
Classifier: Topic :: Software Development :: Libraries :: Python Modules
Requires-Dist: python-dotenv>=1.0.0
Requires-Dist: typer>=0.9.0
Requires-Dist: pygithub>=2.1.1
Requires-Dist: pynacl>=1.5.0
Requires-Dist: gitpython>=3.1.0
Requires-Dist: pytest>=7.0.0 ; extra == 'test'
Requires-Dist: pytest-cov>=4.0.0 ; extra == 'test'
Requires-Dist: pytest-asyncio>=0.21.0 ; extra == 'test'
Provides-Extra: test
License-File: LICENSE
Summary: Cryptographically sign Python functions and classes for defense-in-depth security
Keywords: rust,python,decorator,cryptography
Author: Aidan Dyga
License: MIT
Requires-Python: >=3.8
Project-URL: Issues, https://github.com/MCP-Security-Research/pysealer/issues
Project-URL: Repository, https://github.com/MCP-Security-Research/pysealer
